[
  {
    "id": "200189",
    "category": "IN-024「Apple Pay」プロモーションについて",
    "title": "2026/04/01 12:00",
    "date": "インストアメディアチーム",
    "department": "200411",
    "body": "実施する作業\nNo.\n実施予定日\n作業内容\n実施状況\n作業実施者\n最終更新日\n1\n2026/03/30\n「Apple Pay  レジスイングPOP」ツール到着確認（未着の場合はすかいらーく従業員サイトより依頼してください\n未\n13:19\n2\n2026/03/31\n「Apple Pay  レジスイングPOP」ツール設置＆回答フォーム入力\n未\n13:19\n3\n2026/05/28\n「Apple Pay  レジスイングPOP」ツール撤去\n未\nインストアメディア通達\n商品本部\n2026/05/31\nMD　加藤　志門\n※必要時のみ印刷して掲示する\n主旨\nいつもインストアメディア事業へのご協力ありがとうございます。\n実施案件が決定しましたので、下記内容をご確認のうえ、実施していただけますようお願いいたします。\n※未掲出は契約違反となり、すかいらーくの信用を失いますので必ず掲出・設置報告を実施してください。\n内容\n1.　確認・実施事項一覧表\n2.　概要\n(1) 広告主\nApple Japan合同会社　様\n(2) 掲出期間\n掲出作業日：3月31日（火）オープン後～15時まで\n掲出終了日：5月28日（木）　オープン以降に撤去\n(3) 実施内容\n使用媒体　：レジスイングPOP\n(4) そのほか\n①ツール納品について\n・納品方法　：　3月30日（月）までに配送かばんで納品いたします。\n・数量　　　：　レジスイングPOP　1包（3枚）\n②ツールの再送依頼方法について\n・ツールが未着などで再送依頼をする際は、\nすかいらーく従業員サイト＞各種申請・その他＞ｲﾝｽﾄｱﾂｰﾙ再送手配より再送依頼をしてください。\n③掲出作業について\n・3月31日（火）オープン後から15時の間で添付文書どおりの掲出をお願いいたします。\n④設置報告について\n・3月31日（火）17時までに本通達文書の最下段にある回答フォームから報告をお願いいたします。\n③店舗収益について\n・約11,000円/店あたり\n⑤ツール撤去について\n・5月28日（木）オープン以降順次撤去をお願いいたします。\n本通達のお問い合わせ先\nインストアメディアチーム　　IP:9#100-5582 /Tel:0422‐37‐5282（平日9時～18時）\nインストアメディアツール再送手配手順書\n【Apple Pay_レジスイングPOP】設置方法\n回答フォーム\n回答フォームを印刷する\n➀「Apple Pay」のスイングPOPをレジに1箇所取り付けた\nはい\n*\n➁レジに掲出した画像を添付してください\n*\n画像ファイル選択\n③セルフレジがある場合は掲出の画像を添付してください\n画像ファイル選択\n回答を一時保存する\n回答する\n29",
    "pdfs": [
      {
        "filename": "インストアメディアツール再送手配手順書.pdf",
        "type": "manual",
        "text": "【インストアメディアツール再送手順】\n➀TODまたは業務スマホで\n『すかいらーく従業員サイト』をタップする\n②トップ画面左上の『≡』をタップする\n※TODの向き（縦・横）によって右上に表示される場合があります\n③『各種申請・その他』をタップする\n➃『インストアメディア再送手配』を\nタップする\n⑤必要事項を入力し、送信を\n・再送ツールの種類\n・インストアメディア開始日\n・プロモーション名\nタップして、送信完了を確認する\n・店舗コード\n・ブランド\n・店舗名\n・入力者名"
      },
      {
        "filename": "【Apple Pay_レジスイングPOP】設置方法.pdf",
        "type": "manual",
        "text": "【使用ツールと納品数量】\n【掲出方法】\n掲出作業日\n3月31日（火）オープン後～15時の間\n設置報告日\n3月31日（火）17時までにすかいらーくポータルから回答\n【レジスイングPOP】\n3枚\n①レジスイングPOP\n【レジ】\n【セルフレジ】\n【設置手順】\n①レジ、セルフレジにスイングPOPの添付場所（画面が隠れない場所）があるか確認する\n②上記で確認した各レジ1台につき1箇所にPOSスイングPOP1枚ずつを貼付する\n※セルフレジが複数台ある場合は最大3か所（各レジ1台につき1枚）貼付する\n④残りがある場合は予備として店舗保管し、スイングPOPが劣化、破損時のメンテナンスで使用する\n納品日と納品方法：3月30日（月）まで配送カバンにて納品"
      }
    ],
    "schedules": [
      {
        "date": "2026-04-01",
        "date_type": "schedule",
        "description": "2026/04/01 12:00 実施する作業 No. 実施予定日 作業内容 実"
      },
      {
        "date": "2026-03-30",
        "date_type": "schedule",
        "description": "実施予定日 作業内容 実施状況 作業実施者 最終更新日 1 2026/03/30 「Apple Pay  レジスイングPOP」ツール到着確認"
      },
      {
        "date": "2026-03-31",
        "date_type": "info",
        "description": "らーく従業員サイトより依頼してください 未 13:19 2 2026/03/31 「Apple Pay  レジスイングPOP」ツール設置＆回"
      },
      {
        "date": "2026-05-28",
        "date_type": "deadline",
        "description": "グPOP」ツール設置＆回答フォーム入力 未 13:19 3 2026/05/28 「Apple Pay  レジスイングPOP」ツール撤去 未"
      },
      {
        "date": "2026-05-31",
        "date_type": "info",
        "description": "グPOP」ツール撤去 未 インストアメディア通達 商品本部 2026/05/31 MD　加藤　志門 ※必要時のみ印刷して掲示する 主旨 いつ"
      }
    ],
    "fetched_at": "2026-03-31T16:32:32.006753"
  },
  {
    "id": "199334",
    "category": "IN-016「SBI証券」プロモーションについて",
    "title": "「SBI証券」ツール撤去",
    "date": "2026/03/31",
    "department": "岩永　飛鳥",
    "body": "1週間以内に公開された通達のうち 15件 が未読です。",
    "pdfs": [],
    "schedules": [],
    "fetched_at": "2026-03-31T15:52:15.719466"
  },
  {
    "id": "199336",
    "category": "IN-018「よみきかせキャンバス」プロモーションについて",
    "title": "【よみきかせキャンバス】ツール撤去",
    "date": "2026/03/31",
    "department": "岩永　飛鳥",
    "body": "1週間以内に公開された通達のうち 15件 が未読です。",
    "pdfs": [],
    "schedules": [],
    "fetched_at": "2026-03-31T15:52:15.719466"
  },
  {
    "id": "200411",
    "category": "IN-025B「宮崎市」プロモーションについて",
    "title": "【宮崎市】ツール設置＆回答フォーム入力",
    "date": "2026/03/31",
    "department": "岩永　飛鳥",
    "body": "実施する作業\nNo.\n実施予定日\n作業内容\n実施状況\n作業実施者\n最終更新日\n1\n2026/03/30\n【宮崎市】ツール到着確認（未着の場合はすかいらーく従業員サイトより再送依頼）\n未\n13:19\n2\n2026/03/31\n【宮崎市】ツール設置＆回答フォーム入力\n未\n13:19\n3\n2026/04/14\n【宮崎市】ツール撤去\n未\nインストアメディア通達\n商品本部\n2026/05/01\nMD　加藤　志門\n※必要時のみ印刷して掲示する\n主旨\nいつもインストアメディア事業へのご協力ありがとうございます。\n実施案件が決定しましたので、下記内容をご確認のうえ、実施していただけますようお願いいたします。\n※未掲出は契約違反となり、すかいらーくの信用を失いますので必ず掲出・設置報告を実施してください。\n内容\n1.　確認・実施事項一覧表\n2.　概要\n(1) 広告主・訴求内容\n宮崎市　様　（ふるさと納税の訴求）\n(2) 実施期間\n掲出作業日　　：3月31日（火）オープン～15時まで\nツール撤去日　：4月14日（火）営業時間中\n(3) 実施内容\n使用媒体　：テーブルスタンド（パンフレットなし）\n(4) そのほか\n①ツール納品について\n・納品方法　：3月30日（月）までに配送カバンで納品いたします。\n※取り忘れに注意してください\n・数量　　　：スタンドシート　1束（1束＝50枚）\n②ツールの再送手配方法について\n・ツールが未着などで再送依頼をする際には、\nすかいらーく従業員サイト＞各種申請・その他＞⑪ｲﾝｽﾄｱﾂｰﾙ再送手配より再送依頼をしてください。\n③店舗収益について\n・成果報酬の案件になります。\n④掲出作業について\n・3月31日（火）オープンから15時までの間に添付文書どおりに掲出をお願いいたします。\n⑤設置報告について\n・3月31日（火）17時までに本通達最下段にある回答フォームより回答をお願いいたします。\n⑥ツール撤去について\n・4月14日（火）オープンから営業終了時間までに撤去をお願いいたします。\n※シート右上の日付は『20250512』と記載していますが、撤去をお願いいたします。\n本通達のお問い合わせ先\nインストアメディアチーム　　IP:9#100-5582/TEL:0422-37-5282 （平日9時～18時）\nインストアメディアツール再送手配手順書\n回答フォーム\n回答フォームを印刷する\n「インストアメディア」報告\n①「宮崎市」のスタンドシートをテーブルスタンドに設置した。\nはい\n*\n②掲出の画像を添付してください。\n※撮影時の注意点を確認してください\n*\n画像ファイル選択\n回答を一時保存する\n回答する\n36",
    "pdfs": [
      {
        "filename": "インストアメディアツール再送手配手順書.pdf",
        "type": "manual",
        "text": "【インストアメディアツール再送手順】\n➀TODまたは業務スマホで\n『すかいらーく従業員サイト』をタップする\n②トップ画面左上の『≡』をタップする\n※TODの向き（縦・横）によって右上に表示される場合があります\n③『各種申請・その他』をタップする\n➃『インストアメディア再送手配』を\nタップする\n⑤必要事項を入力し、送信を\n・再送ツールの種類\n・インストアメディア開始日\n・プロモーション名\nタップして、送信完了を確認する\n・店舗コード\n・ブランド\n・店舗名\n・入力者名"
      }
    ],
    "schedules": [
      {
        "date": "2026-03-30",
        "date_type": "schedule",
        "description": "実施予定日 作業内容 実施状況 作業実施者 最終更新日 1 2026/03/30 【宮崎市】ツール到着確認（未着の場合はすかいらーく従業員サ"
      },
      {
        "date": "2026-03-31",
        "date_type": "deadline",
        "description": "すかいらーく従業員サイトより再送依頼） 未 13:19 2 2026/03/31 【宮崎市】ツール設置＆回答フォーム入力 未 13:19 3"
      },
      {
        "date": "2026-04-14",
        "date_type": "deadline",
        "description": "【宮崎市】ツール設置＆回答フォーム入力 未 13:19 3 2026/04/14 【宮崎市】ツール撤去 未 インストアメディア通達 商品本部"
      },
      {
        "date": "2026-05-01",
        "date_type": "info",
        "description": "【宮崎市】ツール撤去 未 インストアメディア通達 商品本部 2026/05/01 MD　加藤　志門 ※必要時のみ印刷して掲示する 主旨 いつ"
      },
      {
        "date": "0422-37-52",
        "date_type": "info",
        "description": "ストアメディアチーム　　IP:9#100-5582/TEL:0422-37-5282 （平日9時～18時） インストアメディアツール再送手配"
      }
    ],
    "fetched_at": "2026-03-31T16:32:32.006753"
  },
  {
    "id": "200226",
    "category": "連絡",
    "title": "【26年4月度】グローバルクルー勉強会の開催について",
    "date": "2026/03/30 18:00",
    "department": "営業政策チーム",
    "body": "主旨\nオンライン「グローバルクルー勉強会」の開催についてお知らせします。\n≪テーマ≫　個人衛生の大切さ\n≪内容≫　みんなが守るべき３つの個人衛生について、勉強します！\n参加エントリーサイトはこちら\n※ストコンからはエントリーできません。TODまたは業務用スマホからお願いします\n内容\n1.開催の背景・目的\n「感じよい勉強会」では、ペースが速くてグローバルクルーの方には難しいとの意見を頂いております。\nそこでこの度、少し日本語が苦手な方を対象として「グローバルクルー勉強会」を開催します。\n※日本語でゆっくり行いますが、日本語検定4級以下の方は、サポートの方との参加を推奨します\n2.対象者\n・グローバルクルー\n・グローバルクルー在籍（予定）店舗の正社員の方\n・グローバルクルーのトレーナーの方\n3.開催日程\n4\n月21(火)、22日(水)、23日(木)、24日(金) 　※\n勉強会本編は約50分\n※時間帯は18時～　19時半～　21時からの1日3開催実施します\n4.参加エントリー方法について\n本通達主旨欄のリンクから参加エントリーをしてください。\n※エントリー登録の名前は、ネームプレートの名前でお願いします\n5.エントリーフォームの注意点について\nエントリーフォームの1ページ目には、「開催回」「開催日」「開催時間」が自動的に表示されます。\n1ページ目はメールのチェックを入れて、内容は変更せずに「次へ」を押してお進みください。\n表示されている日時が違う場合は、一度画面を閉じて、再度正しい日時よりエントリーをお願いいたします。\n※フォームの日時はシステムと連動しているため、画面上で直接修正してもご希望の日時へは変更されません\n6.参加エントリー期限と招待メールについて\n参加エントリー期限は各開催日前日の17時までです。招待メールは前日の20時までに送ります。\n※招待メールが届かない場合は通達の連絡先（感じよい勉強会事務局）までご連絡ください\n7.当日の参加方法と注意点について\n・\n参加する際は、本通達添付の「勉強会メモ」を作表してご準備ください。\n・同じ時間に同一の室内で参加される場合は、1台のTODでご参加ください。\n※日本語検定4級以下の方は、サポートの方との参加を推奨します\n・GoogleMeetで実施します。\nGoogleカレンダーの対象日時、または\n招待メールから\nご参加\nお願いします。\n※前日や翌日、違う開催回のMeetに入らないように注意して下さい\n■Googleカレンダーから\n■招待メールから\n8.【重要】労働時間補正について\n労働時間は1ヶ月最大、5時間まで補正いたします。\n詳細は別途通達でお知らせします。\n※参加エントリー実績のある店舗のみ、労働時間補正の通達を発行いたします\n本通達のお問い合わせ先\nグローバルクルー勉強会事務局　　IP:9#100-1789（営業政策チーム直通）/TEL:0422-37-5377（総合窓口）平日9時～18時\nグローバルクルー勉強会翻訳機能設定方法\n📝 第1回グローバルクルー勉強会 メモ_\n〜 4月30日(木)\n36",
    "pdfs": [],
    "schedules": [
      {
        "date": "2026-03-30",
        "date_type": "info",
        "description": "勉強会 グローバルクルー グローバルクルー　勉強会 公開日 2026/03/30 18:00 〜 タイトル 【26年4月度】グローバルクルー"
      },
      {
        "date": "2026-04-30",
        "date_type": "deadline",
        "description": "一般クルー 連絡文書 発行部門 営業政策グループ 掲示期限 2026/04/30 発行責任者 ディレクター　曳地 ​裕次 ※必要時のみ印刷し"
      },
      {
        "date": "0422-37-53",
        "date_type": "info",
        "description": "IP:9#100-1789（営業政策チーム直通）/TEL:0422-37-5377（総合窓口）平日9時～18時 グローバルクルー勉強会翻訳"
      },
      {
        "date": "2026-08-08",
        "date_type": "info",
        "description": "て データ通信中です。しばらくお待ちください。 通達 戻る 8/8 未読にして戻る ​ ​ その他の操作 リンクをコピーする"
      }
    ],
    "fetched_at": "2026-03-31T15:52:15.719466"
  },
  {
    "id": "200435",
    "category": "連絡",
    "title": "資さんうどんのご家族優待券 利用開始について",
    "date": "2026/03/30 10:00",
    "department": "人事サービスチーム",
    "body": "主旨\n資さんうどんでご家族優待券が利用できるようになりますので、ご確認ください。\n内容\n1．変更時期\n4月1日（水）より利用可能\n※熊本県の八代旭中央通店のみ、4月8日（水）より利用可能\n2．券面変更\n4月配布分（有効期限が5月末）より、表面と裏面に資さんうどんが記載\n【表面】　　　　　　　　　　　　　　　　　　　　　【裏面】\n3．注意事項\n・4月に資さんうどんを利用する場合は、券面に記載がないご家族優待券でも利用できます。\n・ご家族優待券をネットオークション等で転売することは、社内規程により禁じられています。\n本通達のお問い合わせ先\n政策・制度チーム   IP　9#100-5568　/　TEL：0422-37-5190（平日9時～18時）",
    "pdfs": [],
    "schedules": [
      {
        "date": "2026-03-30",
        "date_type": "deadline",
        "description": "録する 店舗メモを登録する ​ キーワード その他 公開日 2026/03/30 10:00 〜 タイトル 資さんうどんのご家族優待券 利用"
      },
      {
        "date": "2026-05-31",
        "date_type": "deadline",
        "description": ", 一般クルー 連絡文書 発行部門 人事総務本部 掲示期限 2026/05/31 発行責任者 MD　武井　一朗 ※必要時のみ印刷して掲示する"
      },
      {
        "date": "0422-37-51",
        "date_type": "info",
        "description": "策・制度チーム   IP　9#100-5568　/　TEL：0422-37-5190（平日9時～18時） 戻る 未読にして戻る ​ ​ その"
      },
      {
        "date": "2026-04-01",
        "date_type": "info",
        "description": "るようになりますので、ご確認ください。 内容 1．変更時期 4月1日（水）より利用可能 ※熊本県の八代旭中央通店のみ、4月8日（"
      },
      {
        "date": "2026-04-08",
        "date_type": "deadline",
        "description": "4月1日（水）より利用可能 ※熊本県の八代旭中央通店のみ、4月8日（水）より利用可能 2．券面変更 4月配布分（有効期限が5月"
      },
      {
        "date": "2026-08-09",
        "date_type": "info",
        "description": "て データ通信中です。しばらくお待ちください。 通達 戻る 8/9 未読にして戻る ​ ​ その他の操作 リンクをコピーする"
      }
    ],
    "fetched_at": "2026-03-31T15:52:15.719466"
  },
  {
    "id": "200850",
    "category": "連絡",
    "title": "2026年4月給与改定および給与決定通知書の配信について",
    "date": "2026/03/27 18:00",
    "department": "政策・制度チーム",
    "body": "主旨\n2026年4月の給与改定および給与決定通知書の配信についてお知らせします。\n昇降給・昇降格の詳細については、人事制度ガイドブック（14～15P）をご確認ください。\n内容\nⅠ．定期格付について\n1．定期格付時の\n昇降給\n昇降給は、原則 「年間総合評価」と「昇降給率表」によって決定します。\n昇降給率表の詳細は、人事制度ガイドブック（14P）をご確認ください。\n2．定期格付時の\n昇降格\n昇降格（等級）については、業績評価の結果をもとに「符号判定」の仕組みを用いて判断します。\n3．フィードバックについて\n以下の内容について、人事総務本部より各上長宛にフィードバックをします。\n上長の方は、4月19日（日）までに、フィードバックをお願いします。\nⅡ．１等級社員のみなし残業について\n2026年4月より１等級社員に10時間分のみなし残業代を支給します。\n(定期格付、ベアを反映した月例給に対して、みなし残業代を上乗せ)\n今回の改定において、不利益変更はございません。\n【導入目的】\n残業10時間分を「みなし残業」として給与に組み込むことで、\n状況に応じた柔軟な働き方と正しい勤怠打刻の推進を実現すること。\nⅢ．給与決定通知書の配信について\n2026年4月からの月例給は「給与決定通知書」にてお知らせします。\nSmartHRにデータを配信します\nので、各自ご確認ください。\n１．配信日\n2026年4月24日（金）\n２．閲覧方法\n下記の手順でSmartHRよりご確認ください\n３． その他\n・人事異動等により給与決定通知書の記載内容から変更となる場合があります\n・退職予定の方へは配信いたしません\n・配信日以降にデータが表示されない場合は、本通達の問い合わせ先にご連絡ください\n本通達のお問い合わせ先\n政策・制度チーム　　IP:9#100-5568／TEL:0422-37-5190（平日9時～18時）",
    "pdfs": [],
    "schedules": [
      {
        "date": "2026-04-24",
        "date_type": "info",
        "description": "データを配信します ので、各自ご確認ください。 １．配信日 2026年4月24日（金） ２．閲覧方法 下記の手順でSmartHRよりご確認く"
      },
      {
        "date": "2026-03-27",
        "date_type": "deadline",
        "description": "舗メモを登録する ​ キーワード 評価・規則・制度 公開日 2026/03/27 18:00 〜 タイトル 2026年4月給与改定および給与"
      },
      {
        "date": "2026-04-30",
        "date_type": "deadline",
        "description": "・リーダー以上 連絡文書 発行部門 人事総務本部 掲示期限 2026/04/30 発行責任者 MD　武井 ​一朗 ※必要時のみ印刷して掲示す"
      },
      {
        "date": "0422-37-51",
        "date_type": "info",
        "description": "先 政策・制度チーム　　IP:9#100-5568／TEL:0422-37-5190（平日9時～18時） 戻る 未読にして戻る ​ ​ その"
      },
      {
        "date": "2026-04-19",
        "date_type": "deadline",
        "description": "総務本部より各上長宛にフィードバックをします。 上長の方は、4月19日（日）までに、フィードバックをお願いします。 Ⅱ．１等級社員"
      },
      {
        "date": "2026-08-10",
        "date_type": "info",
        "description": "て データ通信中です。しばらくお待ちください。 通達 戻る 8/10 未読にして戻る ​ ​ その他の操作 リンクをコピーする"
      }
    ],
    "fetched_at": "2026-03-31T15:52:15.719466"
  },
  {
    "id": "199695",
    "category": "連絡",
    "title": "オンライン面接URL変更について",
    "date": "2026/03/27 10:00",
    "department": "クルー採用チーム",
    "body": "主旨\nオンライン面接URLの変更についてお知らせします。\n内容\nオンライン面接URLの変更について\n現在使用していますオンライン面接URLの有効期限が切れますので、新しいオンライン面接URLを発行します。\n【現オンライン面接URLと新オンライン面接URLについて】\n・現オンライン面接URL：4月14日（火）の面接日まで使用可\n・新オンライン面接URL：4月15日（水）の面接日以降使用可\n※4月15日以降は、必ず新しいオンライン面接URLをお使いください。\n※面接時間から5分を経過しても、応募者様が入室しない場合は、必ずお電話をお願いします。\n本通達のお問い合わせ先\nクルー採用チーム　0422-50-3145　　IP:9#100-5576　　（平日9時～18時）\n22",
    "pdfs": [],
    "schedules": [
      {
        "date": "2026-03-27",
        "date_type": "info",
        "description": "ルー採用 面接 クルー求人 採用（正社員・クルー） 公開日 2026/03/27 10:00 〜 タイトル オンライン面接URL変更について"
      },
      {
        "date": "2026-04-30",
        "date_type": "deadline",
        "description": "・リーダー以上 業務通達 発行部門 人事総務本部 掲示期限 2026/04/30 発行責任者 MD　武井　一朗 ​※必要時のみ印刷して掲示"
      },
      {
        "date": "0422-50-31",
        "date_type": "info",
        "description": "をお願いします。 本通達のお問い合わせ先 クルー採用チーム　0422-50-3145　　IP:9#100-5576　　（平日9時～18時）"
      },
      {
        "date": "2026-04-14",
        "date_type": "deadline",
        "description": "新オンライン面接URLについて】 ・現オンライン面接URL：4月14日（火）の面接日まで使用可 ・新オンライン面接URL：4月15"
      },
      {
        "date": "2026-04-15",
        "date_type": "deadline",
        "description": "月14日（火）の面接日まで使用可 ・新オンライン面接URL：4月15日（水）の面接日以降使用可 ※4月15日以降は、必ず新しいオン"
      },
      {
        "date": "2026-06-11",
        "date_type": "info",
        "description": "て データ通信中です。しばらくお待ちください。 通達 戻る 6/11 未読にして戻る ​ ​ その他の操作 リンクをコピーする"
      }
    ],
    "fetched_at": "2026-03-31T15:52:15.719466"
  },
  {
    "id": "200691",
    "category": "業務",
    "title": "4月度　RS安全運転の実施について【GT】",
    "date": "2026/03/27 10:00",
    "department": "ＲＳ・ＴＯオペレーションチーム",
    "body": "主旨\n店舗全員でRS安全運転行動を理解し、実施しましょう\n安全運転の実施には、ＲＳメンバーだけでなくＥＩメンバー含めた店舗全員の協力が不可欠です\nみなさんで協力して事故０を目標に取り組んでいきましょう\n内容\n4月度安全運転動画は「初期訓練を必ず実施しよう」です\n本動画を確認し初期訓練実施の重要性を理解してください\n交通事故の多くは入社半年未満の方が多く、知識不足が原因です\n入社後、初期訓練を必ず実施し交通事故撲滅していきましょう\n1. 4\n月度　重点行動目標\n2. 動画視聴について\n動画の公開日は、4月1日(水)です　従業員全員が動画視聴をし、安全運転の啓蒙をお願いします\nABILI/ToDo/020_【RS】安全運転重点行動目標/010_2026年/01_【RS】2026年4月（\n初期訓練を必ず実施しよう\n）（動画）\nクリップで検索して視聴すると、視聴履歴が残らないため必ずToDoより検索し、視聴してください\n3. 今月のセーフティートレーナー実施シナリオ\n『sk_(1\n) 信号有交差点』\nアプリ内のユーザーIDはご自身の『10ケタ社員コード』（従業員ID）を使用してトレーニングください\nセーフティートレーナーの店舗実施率と動画視聴率について、店舗TODで確認が出来ます\nセーフティートレーナーと動画視聴を100％実施できるように確認してください\n4. RS無事故カレンダー\n(1)\n無事故カレンダー下部のサインについて、以下の手順を\n確認してください\n①\nMGR(AM)と\nRS勤務者全員の名前と初回勤務日を記入する\n②-1　セーフティートレーナーを\n当月初回勤務日に視聴\nし、視聴日を記入する\n②-2　セーフティートレーナーが100%正解したら、日付を記入する\n③　安全運転動画を\n当月初回勤務日に視聴\nし、視聴日を記入する\n(2)手洗い器周辺もしくはRS備品定位置周辺に掲示してください\n添付の無事故カレンダーを作表して掲示し、デリバリー車両の無事故日数を記入してください。\n※日付の枠内にマジックで連続無事故日数を書き込んでいく\n事故がおきてしまったら、その日は「×」を記入する\n５.セーフティートレーナー実績について\n現在使用していただいている「セーフティートレーナー実績」についてですが\n安全運転動画の視聴実績は、在籍クルーさんの管理店に反映される仕組みになっております\n複数店勤務、ヘルプクルー、すぽくるクルーの方々の実績は管理店にてご確認下さい\nエリアクルーの方は、実施しても実績が反映されませんので、MGRに視聴した事を動画内容と一緒に報告して下さい\nセーフティートレーナー実施率・安全運転動画視聴率の履歴は\n毎週日曜日\nまでの履歴が、\n翌週の火曜日\nに反映されます\n（月曜日に実施した場合は、翌週の火曜日に反映されます）\n本通達のお問い合わせ先\nＲＳ･ＴＯオペレーションチーム IP:9#100-5199 　外線:0422-37-5199　（平日9時～18時）\n【無事故カレンダー】2026年4月(初期訓練を必ず実施しよう)\n〜 4月3日(金)\n24",
    "pdfs": [],
    "schedules": [
      {
        "date": "2026-03-27",
        "date_type": "schedule",
        "description": "ーワード RS RS無事故カレンダー RS安全運転 公開日 2026/03/27 10:00 〜 タイトル 4月度　RS安全運転の実施につい"
      },
      {
        "date": "2026-04-30",
        "date_type": "deadline",
        "description": "クルー 業務通達 発行部門 営業サポートグループ 掲示期限 2026/04/30 発行責任者 ディレクター　林田　洋一 ​※必要時のみ印刷し"
      },
      {
        "date": "0422-37-51",
        "date_type": "info",
        "description": "Ｏオペレーションチーム IP:9#100-5199 　外線:0422-37-5199　（平日9時～18時） 【無事故カレンダー】2026年4"
      },
      {
        "date": "2026-04-03",
        "date_type": "deadline",
        "description": "する 印刷する 作業を登録する 店舗メモを登録する ​ 〜 4月3日(金) キーワード RS RS無事故カレンダー RS安全運転"
      },
      {
        "date": "2026-04-01",
        "date_type": "info",
        "description": "月度　重点行動目標 2. 動画視聴について 動画の公開日は、4月1日(水)です　従業員全員が動画視聴をし、安全運転の啓蒙をお願い"
      },
      {
        "date": "2026-06-10",
        "date_type": "info",
        "description": "】 データ通信中です。しばらくお待ちください。 通達 戻る 6/10 未読にして戻る ​ ​ その他の操作 リンクをコピーする"
      }
    ],
    "fetched_at": "2026-03-31T15:52:15.719466"
  },
  {
    "id": "200493",
    "category": "業務",
    "title": "【売店商品】一部商品の返品のお願いと価格変更の連絡",
    "date": "2026/03/27 10:00",
    "department": "(株)SD&M",
    "body": "実施する作業\nNo.\n実施予定日\n作業内容\n実施状況\n作業実施者\n最終更新日\n1\n2026/04/01\n2026/04/09\n返品対象商品を返品する\n未\n2\n2026/04/10\n値引き対象商品のプライスカードを掲示する\n未\n業務通達\nSD&M\n2026/04/30\n経営企画部長　田中義宏\n​※必要時のみ印刷して掲示\n主旨\n売店商品のロス対策のため、対象商品を返品してください。また一部の商品の価格を変更します。\n対象商品が既に完売している場合は対応は不要です。\n内容\n1．返品対象商品\nベラボットステッカー各種（小5種・大3種）\nベラボットふせん3種\n■ 返品手順\n① 3月末まで棚卸をしてください。\n② 4月1日～9日の間に、添付の返品用紙を使用して返品してください。\n③ 陳列ボードは店舗で破棄してください。\n2．価格変更対象商品\n■ 値引き手順\n① 4月10日のレジオープンから価格が変更されます。\n② プライスカードを添付の新価格のものに差し替えてください。\n③ 棚卸は元価格で実施してください。\nお手数お掛けしてしまいますが、ご対応をお願いします。\n空いたスペースに陳列する商品を発注して、充分な品揃えをお願いします。\n本通達のお問い合わせ先\nSD&M売店チーム　　IP:9#210-302/0422-37-5809（平日9時～18時）\nねこロボステッカー、ふせん返品用紙\nプライスカード\n〜 3月31日(火)",
    "pdfs": [],
    "schedules": [
      {
        "date": "2026-03-27",
        "date_type": "info",
        "description": "ワード 売店 フェア 送り込み その他 菓子 返品 公開日 2026/03/27 10:00 〜 タイトル 【売店商品】一部商品の返品のお願"
      },
      {
        "date": "2026-04-01",
        "date_type": "schedule",
        "description": "実施予定日 作業内容 実施状況 作業実施者 最終更新日 1 2026/04/01 〜 2026/04/09 返品対象商品を返品する 未 2"
      },
      {
        "date": "2026-04-09",
        "date_type": "schedule",
        "description": "状況 作業実施者 最終更新日 1 2026/04/01 〜 2026/04/09 返品対象商品を返品する 未 2 2026/04/10 値引"
      },
      {
        "date": "2026-04-10",
        "date_type": "info",
        "description": "〜 2026/04/09 返品対象商品を返品する 未 2 2026/04/10 値引き対象商品のプライスカードを掲示する 未 業務通達 発"
      },
      {
        "date": "2026-04-30",
        "date_type": "deadline",
        "description": "ードを掲示する 未 業務通達 発行部門 SD&M 掲示期限 2026/04/30 発行責任者 経営企画部長　田中義宏 ​※必要時のみ印刷して"
      },
      {
        "date": "0422-37-58",
        "date_type": "info",
        "description": "い合わせ先 SD&M売店チーム　　IP:9#210-302/0422-37-5809（平日9時～18時） ねこロボステッカー、ふせん返品用紙"
      },
      {
        "date": "2026-03-31",
        "date_type": "deadline",
        "description": "する 印刷する 作業を登録する 店舗メモを登録する ​ 〜 3月31日(火) キーワード 売店 フェア 送り込み その他 菓子 返"
      },
      {
        "date": "2026-07-10",
        "date_type": "info",
        "description": "絡 データ通信中です。しばらくお待ちください。 通達 戻る 7/10 未読にして戻る ​ ​ その他の操作 リンクをコピーする"
      }
    ],
    "fetched_at": "2026-03-31T15:52:15.719466"
  },
  {
    "id": "200769",
    "category": "3月度賞罰委員会報告について",
    "title": "賞罰委員会 ​通達･ポスター貼替",
    "date": "2026/03/26〜04/30",
    "department": "岩永　飛鳥",
    "body": "実施する作業\nNo.\n実施予定日\n作業内容\n実施状況\n作業実施者\n最終更新日\n1\n2026/03/26\n2026/04/30\n賞罰委員会 通達･ポスター貼替\n未\n人事総務本部\n2026/04/30\nＭＤ　武井　一朗\n※必要時のみ印刷して掲示する\n主旨\n3月度賞罰委員会における制裁処分の内容を公表します\n内容\n1．目的\n制裁処分の内容を公表することで、再発を防止すること。\n2．内容\n制裁 2人\n3． 賞罰のポスターについて\nポスターの掲示をお願いいたします。\n会社の規則や法律を遵守して、不正やハラスメントのない職場作りをしましょう。\n4． 相談窓口について\nすかいらーくハラスメント相談窓口（社外） 0120-125-801　 10時～21時（祝日除く）\n労働組合相談ダイヤル（労働組合）    　　 0120-376-227   9時～18時 （年中無休）\nすかいらーくグループ健康相談窓口（社外） 0120-621-860　 24時間 　 （年中無休）\nすかいらーくグループ内部通報窓口（社外） 0120-330-280   12時～21時（平日）\n9時～17時（土日祝）\n本通達のお問い合わせ先\n人事担当チーム　IP：9＃100－5566/TEL：0422-37-5224（平日9時～18時まで）\n3月賞罰委員会ポスター",
    "pdfs": [],
    "schedules": [
      {
        "date": "2026-03-26",
        "date_type": "deadline",
        "description": "を登録する ​ キーワード 表彰・コンテスト・賞罰 公開日 2026/03/26 10:00 〜 タイトル 3月度賞罰委員会報告について 添"
      },
      {
        "date": "2026-04-30",
        "date_type": "schedule",
        "description": "状況 作業実施者 最終更新日 1 2026/03/26 〜 2026/04/30 賞罰委員会 通達･ポスター貼替 未 連絡文書 発行部門 人"
      },
      {
        "date": "0422-37-52",
        "date_type": "deadline",
        "description": "わせ先 人事担当チーム　IP：9＃100－5566/TEL：0422-37-5224（平日9時～18時まで） 3月賞罰委員会ポスター 戻る"
      },
      {
        "date": "2026-04-14",
        "date_type": "info",
        "description": "替 データ通信中です。しばらくお待ちください。 通達 戻る 4/14 未読にして戻る ​ ​ その他の操作 リンクをコピーする"
      }
    ],
    "fetched_at": "2026-03-31T15:52:15.719466"
  },
  {
    "id": "200668",
    "category": "連絡",
    "title": "4月度MSPマネジメント研修（26年新卒以外）について",
    "date": "2026/03/26 18:00",
    "department": "人事・研修チーム",
    "body": "主旨\n【4月度】MSPマネジメント項目を学ぶための研修をオンライン（Meet）で開催します\n下記のリンク（サイト）より、参加申し込みをお願いします　※FC店舗は対象外\n★MSPマネジメント研修（26年新卒以外参加）申し込みサイト★\n内容\n1.今回の内容\n【店舗ミーティング】について\n2.開催日程\n2026年4月16日 （木）22日（水）\n各日　10時：15時　※開催時間は60分です\n3.参加対象者\nMSP「店舗ミーティング」で「知っている」が未取得のアシスタントマネジャーの方はぜひ参加ください\nクルーの方々も参加可能です（クルー版MSPも同様の項目があります）\n※「店舗ミーティング」項目が取得済みのアシスタントマネジャー（マネジャー）も参加可能です\n※26年新卒の方は対象外です（別途、必須MSPマネジメント研修があります）\n4.参加エントリーについて\n主旨欄にあるリンク（サイト）より、いずれの開催日を選び、1人1枠に申し込みをお願いします\n参加エントリー期限は各開催日の前日昼12時まで、招待メールは前日の20時までに送付します\n※参加エントリーは、必ず自店舗TODまたはご自身の業務用スマホで実施してください\n5.その他・準備物など\n・当日までにテキストの印刷をお願いします\n（SKポータル書庫に4月10日までに格納しますので「MSPマネジメント研修」で検索してください）\n・申し込み後の日程変更は新たにご希望の開催枠に、再度申し込みをしてください（変更連絡は不要です）\n本通達のお問い合わせ先\n人事研修チーム　IP:9#100-1789/TEL: 0422‐37‐5377（平日9時～18時）",
    "pdfs": [],
    "schedules": [
      {
        "date": "2026-04-16",
        "date_type": "schedule",
        "description": "1.今回の内容 【店舗ミーティング】について 2.開催日程 2026年4月16日 （木）22日（水） 各日　10時：15時　※開催時間は60"
      },
      {
        "date": "2026-03-26",
        "date_type": "info",
        "description": "ネジメント、WEB教育、研修、トレーニング、MSP 公開日 2026/03/26 18:00 〜 タイトル 4月度MSPマネジメント研修（2"
      },
      {
        "date": "2026-04-30",
        "date_type": "deadline",
        "description": "一般クルー 業務通達 発行部門 営業政策グループ 掲示期限 2026/04/30 発行責任者 ディレクター　曳地　裕次 ​※必要時のみ印刷し"
      },
      {
        "date": "2026-04-10",
        "date_type": "deadline",
        "description": "当日までにテキストの印刷をお願いします （SKポータル書庫に4月10日までに格納しますので「MSPマネジメント研修」で検索してくだ"
      },
      {
        "date": "2026-04-12",
        "date_type": "info",
        "description": "て データ通信中です。しばらくお待ちください。 通達 戻る 4/12 未読にして戻る ​ ​ その他の操作 リンクをコピーする"
      }
    ],
    "fetched_at": "2026-03-31T15:52:15.719466"
  },
  {
    "id": "200415",
    "category": "業務",
    "title": "人事制度説明会の開催について",
    "date": "2026/03/26 18:00",
    "department": "政策・制度チーム",
    "body": "主旨\n2026年度の人事制度改定に関する説明会開催についてお知らせいたします。\n実施概要を確認の上で、ご参加をお願いいたします。\n内容\n１．対象者\n全正社員（必須）　※2026年3月1日以前に入社された方　　※嘱託社員を除く\n２．開催日程\n（オンライン開催：1時間を予定）\n３．内容\n(1) 人事制度改定の目的について\n(2) 改定内容について\n(3) 制度移行について\n(4) まとめ・質疑応答　　　※内容・時間は一部変更となる場合があります\n４．開催方法・申し込み\n説明会はオンライン（Zoomウェビナー）で実施いたします。\n【申し込み方法】\n４月13日（月）までに下記URLまたはQRコードより申し込みをお願いします。\n⇒参加申し込みフォームはこちらをクリック\n※日程変更の場合は再度上記より申し込みをお願いします（キャンセル連絡不要）\n【参加方法】\n下記URLまたはQRコードよりご参加ください（カメラ＆マイクOFFで参加）\n⇒ZoomのURLはこちらをクリック\n本通達のお問い合わせ先\n政策・制度チーム　IP　9#100-5568 / TEL：0422-37-5190 （平日9時～18時）\n〜 4月24日(金)\n25",
    "pdfs": [],
    "schedules": [
      {
        "date": "2026-03-01",
        "date_type": "schedule",
        "description": "をお願いいたします。 内容 １．対象者 全正社員（必須）　※2026年3月1日以前に入社された方　　※嘱託社員を除く ２．開催日程 （オン"
      },
      {
        "date": "2026-03-26",
        "date_type": "schedule",
        "description": "〜 4月24日(金) キーワード 評価・規則・制度 公開日 2026/03/26 18:00 〜 タイトル 人事制度説明会の開催について 発"
      },
      {
        "date": "2026-04-30",
        "date_type": "deadline",
        "description": "・リーダー以上 業務通達 発行部門 人事総務本部 掲示期限 2026/04/30 発行責任者 ＭＤ　武井　一朗 ​※必要時のみ印刷して掲示"
      },
      {
        "date": "0422-37-51",
        "date_type": "info",
        "description": "政策・制度チーム　IP　9#100-5568 / TEL：0422-37-5190 （平日9時～18時） 戻る 未読にして戻る ​ ​ そ"
      },
      {
        "date": "2026-04-24",
        "date_type": "deadline",
        "description": "する 印刷する 作業を登録する 店舗メモを登録する ​ 〜 4月24日(金) キーワード 評価・規則・制度 公開日 2026/03"
      },
      {
        "date": "2026-04-13",
        "date_type": "deadline",
        "description": "（Zoomウェビナー）で実施いたします。 【申し込み方法】 ４月13日（月）までに下記URLまたはQRコードより申し込みをお願いし"
      },
      {
        "date": "2026-04-11",
        "date_type": "info",
        "description": "て データ通信中です。しばらくお待ちください。 通達 戻る 4/11 未読にして戻る ​ ​ その他の操作 リンクをコピーする"
      }
    ],
    "fetched_at": "2026-03-31T15:52:15.719466"
  },
  {
    "id": "200605",
    "category": "業務",
    "title": "【GT】2026年4月度プランドメンテナンスについて",
    "date": "2026/03/26 18:00",
    "department": "ＧＴオペレーション推進チーム",
    "body": "主旨\n設備機器を正常な状態に保ち、お客様に約束したＱＳＣを提供することを目的としたプランドメンテナンス(Planned Maintenance)を実施いたします。\n4月は採用が増える季節に入るため、職場環境の改善と定着率向上のために「ウェルカムクレンリネス」を実施いたします。\n4月20日（月）までに実施し報告をお願いいたします。\n内容\n1. 内容\n4月は「ウエルカムクレンリネス」を実施します。実施清掃箇所と確認項目です。\nフロア・キッチン全員で清掃を行いましょう。\n（1）控室→不用な品や帳票は撤去し、テーブルの上はタブレット・ペーパータオル・ノロスター（プッシュ式）のみ\n（2）掲示物→期限切れや不用な帳票は廃棄し、最新の必要な帳票のみを掲示する\n（3）ロッカー→不用品や使用していないユニフォームは撤去し、ハンガーは必要数を準備する\n（4）更衣室→更衣室内には何も置かず、マットが汚れ・破損している場合は発注する(食器:52725 パズルマット9個)\n（5）下駄箱→使用していない靴は撤去し、使用する棚には従業員の名前をテプラで表示する\n（6）従業員トイレ→不用物は撤去し、トイレリセット清掃を実施する\n2. 実施期限と報告について\n報告期間：4月20日（月）期限\n画像項目については実施後の画像を店舗デバイスで撮影の上、回答フォームに添付し報告ください。\n【撮影箇所】控え室\n【ポイント】控え室全体が分かるように遠目から撮影する\n本通達のお問い合わせ先\nGTオペレーション推進チーム　IP:9#100-5522 /TEL:0422-37-5377（平日9時～18時）\n回答フォーム\n回答フォームを印刷する\n①プランドメンテは完了しましたか？\nはい\n*\n②２S実施後、店舗デバイスで控え室を撮影しご報告ください\n【撮影場所】\n控え室全体が分かるように遠目より撮影\n画像ファイル選択\n回答を一時保存する\n回答する\n〜 4月18日(土)",
    "pdfs": [],
    "schedules": [
      {
        "date": "2026-03-26",
        "date_type": "info",
        "description": ") キーワード 清掃・メンテナンス・点検・リモデル 公開日 2026/03/26 18:00 〜 タイトル 【GT】2026年4月度プランド"
      },
      {
        "date": "2026-04-30",
        "date_type": "deadline",
        "description": "26年4月度プランドメンテナンスについて 回答 回答期限: 2026/04/30 23:59 \t\t\t\t( \t\t\t\t\t店舗ごとに１回答\t\t /"
      },
      {
        "date": "0422-37-53",
        "date_type": "deadline",
        "description": "レーション推進チーム　IP:9#100-5522 /TEL:0422-37-5377（平日9時～18時） 回答フォーム 回答フォームを印刷す"
      },
      {
        "date": "2026-04-18",
        "date_type": "deadline",
        "description": "する 印刷する 作業を登録する 店舗メモを登録する ​ 〜 4月18日(土) キーワード 清掃・メンテナンス・点検・リモデル 公開"
      },
      {
        "date": "2026-04-20",
        "date_type": "deadline",
        "description": "率向上のために「ウェルカムクレンリネス」を実施いたします。 4月20日（月）までに実施し報告をお願いいたします。 内容 1. 内容"
      },
      {
        "date": "2026-05-11",
        "date_type": "info",
        "description": "て データ通信中です。しばらくお待ちください。 通達 戻る 5/11 未読にして戻る ​ ​ その他の操作 リンクをコピーする"
      }
    ],
    "fetched_at": "2026-03-31T15:52:15.719466"
  },
  {
    "id": "200779",
    "category": "業務",
    "title": "【GT】4月発注関連について",
    "date": "2026/03/26 10:00",
    "department": "営業管理チーム",
    "body": "主旨\n4月発注関連と氷用バスケット送り込みについてお知らせします\n内容\n1.対象店舗\n本通達配信店舗\n2.実施日\n4月1日（水）発注より開始\n3.氷用バスケットの送り込みについて\n現在、使用している氷用バスケットは食品への使用安全基準をクリアしていないため入れ替えを実施します\n店舗に新バスケットが届きましたら現行バスケットを廃棄処分してください\n送付期間：4月6日（月）～4月19日（日）\n送付方法：宅配便（4月6日に食器発注した店舗は同梱します）\n※今回送付する氷用バスケットをすでに発注した店舗には送り込みません\n【送付する氷用バスケット画像】\n4.発注関係\n連絡内容\n≪新規品≫\n≪変更品≫\n≪中止品≫\n本通達のお問い合わせ先\n営業管理チーム　　IP:9#100-1837/TEL:0422-37-5377（平日9時～18時）\n18",
    "pdfs": [],
    "schedules": [
      {
        "date": "2026-03-26",
        "date_type": "info",
        "description": "ード オペレーション メニュー・食材・食器・消耗品 公開日 2026/03/26 10:00 〜 タイトル 【GT】4月発注関連について 発"
      },
      {
        "date": "2026-04-30",
        "date_type": "deadline",
        "description": "クルー 業務通達 発行部門 営業サポートグループ 掲示期限 2026/04/30 発行責任者 ディレクター　林田　洋一 ​※必要時のみ印刷し"
      },
      {
        "date": "0422-37-53",
        "date_type": "info",
        "description": "せ先 営業管理チーム　　IP:9#100-1837/TEL:0422-37-5377（平日9時～18時） 戻る 未読にして戻る ​ ​ その"
      },
      {
        "date": "2026-04-01",
        "date_type": "schedule",
        "description": "らせします 内容 1.対象店舗 本通達配信店舗 2.実施日 4月1日（水）発注より開始 3.氷用バスケットの送り込みについて 現"
      },
      {
        "date": "2026-04-06",
        "date_type": "info",
        "description": "届きましたら現行バスケットを廃棄処分してください 送付期間：4月6日（月）～4月19日（日） 送付方法：宅配便（4月6日に食器発"
      },
      {
        "date": "2026-04-19",
        "date_type": "info",
        "description": "バスケットを廃棄処分してください 送付期間：4月6日（月）～4月19日（日） 送付方法：宅配便（4月6日に食器発注した店舗は同梱し"
      },
      {
        "date": "2026-04-13",
        "date_type": "info",
        "description": "て データ通信中です。しばらくお待ちください。 通達 戻る 4/13 未読にして戻る ​ ​ その他の操作 リンクをコピーする"
      }
    ],
    "fetched_at": "2026-03-31T15:52:15.719466"
  },
  {
    "id": "200059",
    "category": "【GT】3月追加販促計画について",
    "title": "残ったくじ付きステッカータンブラーの廃棄",
    "date": "2026/03/26",
    "department": "岩永　飛鳥",
    "body": "1週間以内に公開された通達のうち 15件 が未読です。",
    "pdfs": [],
    "schedules": [],
    "fetched_at": "2026-03-31T15:52:15.719466"
  },
  {
    "id": "200805",
    "category": "業務",
    "title": "【GT】4月追加販促について(クーポンキャンペーン）",
    "date": "2026/03/25 18:00",
    "department": "ＧＴプロモーションチーム",
    "body": "主旨\n4月追加販促について\n春休み明け～GW前の客数が落ち込みやすい時期にクーポンを発行し、来店促進を図ります。\n内容\n1. 4月販促スケジュールについて\n2. 新生活応援クーポンキャンペーンについて\n3. 3月26日(木)～すかいらーくポイントプレゼントキャンペーンの中止について\n本通達のお問い合わせ先\nGTプロモーションチーム　　IP:9#100-5570/TEL:0422-37-5291 （平日9時～18時）\n【GT】4月追加販促について（クーポンキャンペーン）\n17",
    "pdfs": [],
    "schedules": [
      {
        "date": "2026-03-25",
        "date_type": "deadline",
        "description": "店舗メモを登録する ​ キーワード プロモーション 公開日 2026/03/25 18:00 〜 タイトル 【GT】4月追加販促について(ク"
      },
      {
        "date": "2026-04-30",
        "date_type": "deadline",
        "description": "上 , 一般クルー 業務通達 発行部門 商品本部 掲示期限 2026/04/30 発行責任者 MD　加藤　志門 ​※必要時のみ印刷して掲示"
      },
      {
        "date": "0422-37-52",
        "date_type": "info",
        "description": "プロモーションチーム　　IP:9#100-5570/TEL:0422-37-5291 （平日9時～18時） 【GT】4月追加販促について（ク"
      },
      {
        "date": "2026-03-26",
        "date_type": "info",
        "description": "ついて 2. 新生活応援クーポンキャンペーンについて 3. 3月26日(木)～すかいらーくポイントプレゼントキャンペーンの中止につ"
      },
      {
        "date": "2026-04-16",
        "date_type": "info",
        "description": "） データ通信中です。しばらくお待ちください。 通達 戻る 4/16 未読にして戻る ​ ​ その他の操作 リンクをコピーする"
      }
    ],
    "fetched_at": "2026-03-31T15:52:15.719466"
  },
  {
    "id": "200527",
    "category": "連絡",
    "title": "【特別選考のご案内】Recruiting information ~採用情報20...",
    "date": "2026/03/25 18:00",
    "department": "社員採用チーム",
    "body": "主旨\n新卒/中途ですかいらーくへ入社を希望する方、興味がある方を対象に【クルー限定 会社説明会】を開催中です！\nまた、28年卒以降の方に向けて、インターンシップを10コンテンツ以上開催します！\n対象のクルーへ添付のチラシを印刷してお渡しください。\n内容\n１.\n28年卒以降の方向け！インターンシップについて\n店舗運営やマネジメントの体験を通して、すかいらーくビジネスの「現場」と「未来」の両方に触れることができます。\nマネジャー、マーケティングなどのお仕事体験、自己分析や面接対策などの就活サポートをご用意しています。\n2. 会社説明会の開催について\n入社を検討している皆さんを対象に会社説明会を開催します。\n選考に進むか迷っている方でも大歓迎です。まずは、会社説明会にご参加ください！\n【開催日程】\n＼ 新卒採用 ※\n27年卒の方が対象です！\n／　　　　　　　　 ＼ 中途採用 ／\n■4月   9日（木）　16:00～17:00                            ■4月  2日（木）　15:00～16:00\n■4月 22日（水）  11:00～12:00　　　　　　   ■4月  6日（月）　10:00～16:00\n■4月10日（金）　15:00～16:00\n【参加特典】　新卒/中途採用の会社説明会へご参加の方は\n一次面接を免除\nいたします。\n3.予約方法について\n下記QRコードから、ご登録いただいた方へマイページを発行しますのでそちらからご予約ください。\n中途採用　　　　       　　　 新卒採用（27年卒）　　　              新卒採用（28年卒以降）\n本通達のお問い合わせ先\n社員採用チーム　IP:9#100-5569　/　採用フリーダイヤル　0120-133-882 　（平日9時～18時）\nクルー限定チラシ",
    "pdfs": [],
    "schedules": [
      {
        "date": "2026-03-25",
        "date_type": "info",
        "description": "ンターンシップ 採用 社員 採用（クルー・正社員） 公開日 2026/03/25 18:00 〜 タイトル 【特別選考のご案内】Recrui"
      },
      {
        "date": "2026-04-30",
        "date_type": "deadline",
        "description": ", 一般クルー 連絡文書 発行部門 人事総務本部 掲示期限 2026/04/30 発行責任者 MD　武井一朗 ※必要時のみ印刷して掲示する"
      },
      {
        "date": "2026-04-09T16:00",
        "date_type": "info",
        "description": "卒の方が対象です！ ／　　　　　　　　 ＼ 中途採用 ／ ■4月   9日（木）　16:00～17:00"
      },
      {
        "date": "2026-04-02T15:00",
        "date_type": "info",
        "description": "0                            ■4月  2日（木）　15:00～16:00 ■4月 22日（水）  11:00～12:00"
      },
      {
        "date": "2026-04-22T11:00",
        "date_type": "info",
        "description": "■4月  2日（木）　15:00～16:00 ■4月 22日（水）  11:00～12:00　　　　　　   ■4月  6日（月）　10:0"
      },
      {
        "date": "2026-04-06T10:00",
        "date_type": "info",
        "description": "22日（水）  11:00～12:00　　　　　　   ■4月  6日（月）　10:00～16:00 ■4月10日（金）　15:00～16:00 【"
      },
      {
        "date": "2026-04-10T15:00",
        "date_type": "info",
        "description": "■4月  6日（月）　10:00～16:00 ■4月10日（金）　15:00～16:00 【参加特典】　新卒/中途採用の会社説明会へご参"
      },
      {
        "date": "2026-04-09",
        "date_type": "info",
        "description": "卒の方が対象です！ ／　　　　　　　　 ＼ 中途採用 ／ ■4月   9日（木）　16:00～17:00"
      },
      {
        "date": "2026-04-02",
        "date_type": "info",
        "description": "0                            ■4月  2日（木）　15:00～16:00 ■4月 22日（水）  11"
      },
      {
        "date": "2026-04-22",
        "date_type": "info",
        "description": "■4月  2日（木）　15:00～16:00 ■4月 22日（水）  11:00～12:00　　　　　　   ■4月"
      },
      {
        "date": "2026-04-06",
        "date_type": "info",
        "description": "22日（水）  11:00～12:00　　　　　　   ■4月  6日（月）　10:00～16:00 ■4月10日（金）　15:0"
      },
      {
        "date": "2026-04-10",
        "date_type": "info",
        "description": "■4月  6日（月）　10:00～16:00 ■4月10日（金）　15:00～16:00 【参加特典】　新卒/中途採用"
      },
      {
        "date": "2026-04-15",
        "date_type": "info",
        "description": ". データ通信中です。しばらくお待ちください。 通達 戻る 4/15 未読にして戻る ​ ​ その他の操作 リンクをコピーする"
      }
    ],
    "fetched_at": "2026-03-31T15:52:15.719466"
  },
  {
    "id": "200821",
    "category": "業務",
    "title": "2月、3月勤怠アラームリスト",
    "date": "2026/03/25 17:15",
    "department": "健康・労務チーム",
    "body": "主旨\n2月、3月の勤怠データに関するアラームをお知らせいたします。\n特に勤怠データの不備がある場合は正しく給与が支給されません。\n本通達配信店舗は必ず対象者および内容を確認し、期限内に対応をお願いします。\n内容\n１．実施すること\n(1)対象となるアラームを「①アラーム対象者リスト」で確認する\n(2)対象となるアラームの対象者をリスト②～⑤で確認する\n(3)アラームごとに以下の手順に沿って、確認と対応を実施する\n※ヘルプ等で本人が店舗不在の場合でも、必ず本通達の届いた店舗マネジャーが責任を持って連絡・対応してください\n2．有給取得期限リスト（当月期限で年間取得5日未満の方）※\n年10日以上付与された方は1年以内に5日以上の取得が法律で義務\n付けられています。\n(1)当月期限の方は月末までにストコン登録をお願いします。取得期限月ギリギリにならないように計画的に取得してください。\n※「消失日数」＝取得義務ではありません。「取得義務日数」分以外の取得義務はありません。\n※全従業員の年間を通じた有給取得状況は、「人事関連ポータル」の「有給取得予定登録」で確認できます。\n(2)期限：\n当月期限の方は月次送信前までにストコンに有給登録してください。\n(3)問い合わせ先：健康・労務チーム　IP:9#100-5565　TEL:0422-37-5217\n3．翌月計画所定未登録リスト（24日時点で未登録および所定休日数が\n9日以外のアシスタント職\nの方）\n(1)至急、管理店にて登録および修正入力をお願いします。\n(2)期限：\n月次送信前までにストコンに入力\n(3)問い合わせ先：健康・労務チーム　IP:9#100-5565　TEL:0422-37-5217\n※既に登録済み等はご容赦ください。\n＜注意＞\n・異動時の未登録が多発しています。ブランド間異動、新店異動、閉店に関わらず現在の管理店で必ず入力してください。\n・アシスタント職でも毎月自身で登録出来ているかの確認をさせてください。\n・添付のリストに載っていなくても、翌月中に復職予定の方は登録してください。\n4．当月法定休アラームリスト（法定休日出勤が発生している方）\n(1)同一週内（月～日曜）で所定休日がある方は、業務アプリ\n「タイムカード修正正社員」\nで申請をお願いします。\n(2)期限\n：\n3\n月31\n日（火）厳守\n(3)問い合わせ先：人事サービス　正社員給与　IP:9#100-5552　TEL:0422-37-5408\n＜注意＞\n・異動時の実績所定変更ミスが発生していますので、注意してください。\n① 事前に異動先店舗のスケジュールを確認し、異動前店舗にて実績所定の修正をする(転勤休暇は取得後に登録する)\n② 着任日に雇用マスタでヘルプマスタ登録をして個人データを移行（雇用マスタ情報と前月に入力した勤務計画を取込む）\n③ ②を実施後、4日以降に複数店マスタメンテナンスで管理店を変更する(毎月1～3日は変更禁止)\n※着任後、1～3日で実績所定の変更が生じた場合は、管理店（異動前店舗）で修正をする\n※実績所定修正について・・・本人がヘルプ店勤務の場合は、出勤打刻前に管理店を変更してから修正するか、\nできない場合は管理店のマネジャーかクルーに修正依頼をしてください。\n5．当月有給アラームリスト（有給登録日に勤務・打刻実績のある方）\n(1)リストアップされた方は給与確定ができませんので、業務アプリ\n「実績所定修正依頼書」\nで申請後、必ず営業部長に承認をお願いしてください。\n(2)期限：\n3月31日（火\n）昼12時 厳守\n(3)問い合わせ先：健康・労務チーム　IP:9#100-5565　TEL:0422-37-5217\n※ 既に修正依頼をされている場合はご容赦ください。\n＜注意＞\n・実績所定修正依頼書の所定選択肢には「有給」はありません、有給登録前の所定時間（8H等）を入力してください。\n・有給は取得後に登録してください。\n６．\n当月\n13時間超え勤務リスト（1日の勤務時間が13時間を超えている日が発生している方）\n(1)当月勤怠実績において1日の勤務が長時間の方を報告します。\n打刻ミスなどで勤務時間の修正が必要な場合は、忘れずに店舗で勤怠修正を実施してください。\n(2)期限：\n月次送信前までに実施\n本通達のお問い合わせ先\n人事サービス正社員給与　　IP:9#100-5552　TEL:0422-37-5408（平日9時～18時）\n健康・労務チーム　　IP:9#100-5565　TEL:0422-37-5217 （平日9時～18時）\n①アラーム対象者リスト\nストコン店舗CD\n店舗名\n営業部ＣＤ\n営業部名\n②有給取得期限\n③翌月計画未登録\n④法定休\n⑤有給打刻\n⑥13時間超勤務\n018974gt\nＧＴみなとみらい\n14650\nＧＴ横浜営業部\n〇\n②有給取得期限リスト\n配信店舗\n所属CD\n所属名称\n役職\n社員CD\n社員名\n取得期限\n取得義務日数\n取得日数\n有給残日数\n消失日数\n人財本部コメント\n018974gt\n18974\nＧＴみなとみらい\nクルー\n189380179\n山中　友里花\n2026/04/30\n5\n0\n20\n0\n2026/3休職\n018974gt\n18974\nＧＴみなとみらい\nクルー\n189740259\nリアッド\n2026/04/30\n5\n0\n10\n0\n取得期限までに計画的に取得してください。\n③翌月計画所定未登録リスト\n店舗CD（配信）\n所属CD\n所属名\n役職\n社員CD\n社員名\n勤務計画登録\n（数字は公休数）\n表示するデータがありません。\n④当月法定休アラームリスト\n店舗CD（配信）\n所属\nＣＤ\n所属名称\n役職\n社員番号\n社員名称\n勤務日数\n所定休日日数\n法定休日日数\n所定休日出勤日数\n法定休日出勤日数\n法休出勤（合計：当+翌）分\n法休出勤（当日）分\n法休出勤（翌日）分\n表示するデータがありません。\n⑤当月有給勤務アラーム\n配信店舗CD\n所属CD\n所属名\n役職\n社員CD\n社員名\n日付\n実績所定\n(有給登録前)\n勤務実績\n表示するデータがありません。\n⑥当月13時間超え勤務リスト\n配信店舗CD\n就労所属コード\n就労所属名称\n役職\n日付\n社員番号\n社員名称\n実績所定\n始業時刻（実績）\n終業時刻（実績）\n勤務時間\n13時間超え勤務回数\n表示するデータがありません。\n37",
    "pdfs": [
      {
        "filename": "実績所定修正申請マニュアル.pdf",
        "type": "detail",
        "text": ""
      }
    ],
    "schedules": [
      {
        "date": "2026-03-25",
        "date_type": "deadline",
        "description": "舗メモを登録する ​ キーワード その他 アラーム 公開日 2026/03/25 17:15 〜 タイトル 2月、3月勤怠アラームリスト 関"
      },
      {
        "date": "2026-03-31",
        "date_type": "deadline",
        "description": "（アラーム通知・要確認） 発行部門 人事総務本部 掲示期限 2026/03/31 発行責任者 MD　武井　一朗 ※必要時のみ印刷して掲示する"
      },
      {
        "date": "0422-37-52",
        "date_type": "deadline",
        "description": "せ先：健康・労務チーム　IP:9#100-5565　TEL:0422-37-5217 3．翌月計画所定未登録リスト（24日時点で未登録および"
      },
      {
        "date": "0422-37-54",
        "date_type": "info",
        "description": "事サービス　正社員給与　IP:9#100-5552　TEL:0422-37-5408 ＜注意＞ ・異動時の実績所定変更ミスが発生していますの"
      },
      {
        "date": "2026-04-30",
        "date_type": "info",
        "description": "ＧＴみなとみらい クルー 189380179 山中　友里花 2026/04/30 5 0 20 0 2026/3休職 018974gt 18"
      },
      {
        "date": "2026-04-17",
        "date_type": "info",
        "description": "ト データ通信中です。しばらくお待ちください。 通達 戻る 4/17 未読にして戻る ​ ​ その他の操作 リンクをコピーする"
      }
    ],
    "fetched_at": "2026-03-31T15:52:15.719466"
  },
  {
    "id": "200419",
    "category": "連絡",
    "title": "グッドクオリティバッチ受賞者について",
    "date": "2026/03/25 10:00",
    "department": "人事担当チーム",
    "body": "主旨\nグッドクオリティバッチの受賞者についてお知らせいたします。\n内容\n1．目的\nグッドクオリティを表現した社員・クルー・店舗を賞賛し感謝の意を表すことで、\nすかいらーくグループの褒める風土を醸成する。\n2．グッドクオリティバッチ受賞者\nグッドクオリティカードの取得枚数に応じてグッドクオリティバッチを進呈しました。\n受賞者の皆様、おめでとうございます。\n3.  グッドクオリティカードの運用ルール\n（1）発行ルール\n（2）カード登録方法\nすかいらーくポータルの業務アプリから登録してください。\n（3）グッドクオリティバッチの進呈\nグッドクオリティカード取得枚数に応じてグッドクオリティバッチを進呈します。\n（4）カード入手方法\n①営業部長：「_グッドクオリティカード担当」へメールで依頼\n②マネジャー：営業部長から必要数を取得\n本通達のお問い合わせ先\n人事担当チーム   IP 9＃100‐5566 　電話0422-37-5224（平日9時～18時）\nGQB受賞者ﾘｽﾄ2603",
    "pdfs": [],
    "schedules": [
      {
        "date": "2026-03-25",
        "date_type": "deadline",
        "description": "を登録する ​ キーワード 表彰・コンテスト・賞罰 公開日 2026/03/25 10:00 〜 タイトル グッドクオリティバッチ受賞者につ"
      },
      {
        "date": "2026-04-30",
        "date_type": "deadline",
        "description": ", 一般クルー 連絡文書 発行部門 人事総務本部 掲示期限 2026/04/30 発行責任者 MD　武井　一朗 ※必要時のみ印刷して掲示する"
      },
      {
        "date": "0422-37-52",
        "date_type": "info",
        "description": "せ先 人事担当チーム   IP 9＃100‐5566 　電話0422-37-5224（平日9時～18時） GQB受賞者ﾘｽﾄ2603 戻る"
      },
      {
        "date": "2026-04-18",
        "date_type": "info",
        "description": "て データ通信中です。しばらくお待ちください。 通達 戻る 4/18 未読にして戻る ​ ​ その他の操作 リンクをコピーする"
      }
    ],
    "fetched_at": "2026-03-31T15:52:15.719466"
  },
  {
    "id": "200777",
    "category": "連絡",
    "title": "SSS_発注システムの機能改善の延期について",
    "date": "2026/03/24 18:00",
    "department": "店舗ＢＯシステムチーム",
    "body": "主旨\nSSS_発注システムの機能改善について【3月】\nの通達でお知らせした\n本日リリース予定のプログラムに不具合が見つかったためリリースを延期します。\n内容\n本日リリース予定のプログラムに不具合が見つかりました。\n不具合を改修した後に、再度リリースを実施いたします。\n日程については、改めてお知らせいたします。\nご迷惑をおかけして申し訳ございません。\n本通達のお問い合わせ先\nIT総合窓口　  メール：helpdesk_sk_store@skylark.co.jp\n（全日8時～18時）        IP：9#100-5559/TEL:0422-37-5231\n（全日18時～26時）　   TEL：03-6259-1815",
    "pdfs": [],
    "schedules": [
      {
        "date": "2026-03-24",
        "date_type": "deadline",
        "description": "を登録する ​ キーワード SSS 発注 ストコン 公開日 2026/03/24 18:00 〜 タイトル SSS_発注システムの機能改善の"
      },
      {
        "date": "2026-03-31",
        "date_type": "deadline",
        "description": "上 , 一般クルー 連絡文書 発行部門 IT本部 掲示期限 2026/03/31 発行責任者 MD　平野　曉 ※必要時のみ印刷して掲示する"
      },
      {
        "date": "0422-37-52",
        "date_type": "info",
        "description": "18時）        IP：9#100-5559/TEL:0422-37-5231 （全日18時～26時）　   TEL：03-6259-"
      },
      {
        "date": "2026-04-19",
        "date_type": "info",
        "description": "て データ通信中です。しばらくお待ちください。 通達 戻る 4/19 未読にして戻る ​ ​ その他の操作 リンクをコピーする"
      }
    ],
    "fetched_at": "2026-03-31T15:52:15.719466"
  },
  {
    "id": "200156",
    "category": "【売店商品】「新食感フェア」の送り込みについて",
    "title": "商品陳列 ​/ ​POP・プライスカードを掲示",
    "date": "2026/03/23〜26",
    "department": "岩永　飛鳥",
    "body": "1週間以内に公開された通達のうち 15件 が未読です。",
    "pdfs": [],
    "schedules": [],
    "fetched_at": "2026-03-31T15:52:15.719466"
  },
  {
    "id": "200602",
    "category": "業務",
    "title": "【GT】4月度宅配CPの参加について(外部配達)",
    "date": "2026/03/19 18:00",
    "department": "ＲＳ・ＴＯオペレーションチーム",
    "body": "主旨\n出前館SD、UberEats、menuのCP(キャンペーン)に参加します。\n内容\n目次\n1.CPスケジュール\n2.<外部配達>出前館SD半額CP(チーズINハンバーグ弁当)\n3.<外部配達>UberEatsベストディールCP\n4.<外部配達>menuクーポン配布CP\n5.店舗での実施作業\n1.CPスケジュール\n2.<外部配達>出前館SD半額CP\n【目的】出前館サイトで半額CPを実施することにより、宅配事業の売上拡大を目指します。\n(1)CP内容\n期間中「チーズINハンバーグ弁当」を出前館サイトで半額にて販売いたします。\n(2)実施期間\n2026年4月2日(木)～2026年4月8日(水)\n(3)対象店舗\n出前館SD実施店舗\n(4)対象商品\n(5)CP効果予測\n3.<外部配達>UberEatsベストディールCP\n【目的】ベストディールCPに参加することにより、宅配事業の売上拡大を目指します。\n(1)CP内容\n2,000円以上の注文で30％OFF　※割引額の40%はUberEats社に負担していただきます。\n(2)実施期間\n2026年4月14日(火)～2026年4月27日(月)\n(3)対象店舗\nUberEats実施店舗　※UberDirectは対象外\n(4)CP効果予測\n4.<外部配達>menuクーポン配布CP\n【目的】menuクーポン配布CPに参加することにより、宅配事業の売上拡大を目指します。\n(1)CP内容\n1,500円以上の注文で使える500円OFFクーポンを下記期間で配布します。\n※コストは全額menu社に負担していただきます。\n(2)配布期間(クーポン使用可能期間)\n2026年4月27日(月)～2026年5月3日(日)\n(3)対象ユーザー\nPontaパス会員(有料会員)\n(4)対象店舗\nmenu実施店舗\n(5)CP効果予測\n5.店舗での実施作業\n・店舗での特別な作業は発生しませんが、対象の期間はそれぞれの注文が増加します。\n各店舗、ご準備の程よろしくお願いいたします。\n・前回CPの個店別実績を添付いたしますのでご確認をお願いいたします。\n本通達のお問い合わせ先\nRS・TOオペレーションチーム　　IP:9#100-5523  外線:0422-37-5501 （平日9時～18時）\n【通達添付】4月GTキャンペーン前回実績\nTCD\n店舗名\n対象CP\nCP商品名\nCP期間中日商\nCP期間中日件数\nCP期間中販売数/日\n018974gt\nＧＴみなとみらい\n出前館SD半額セール(2月実績)\nチーズINハンバーグ弁当\n3,161円\n1.1件\n0.4食\n〜 4月3日(金)\n27",
    "pdfs": [],
    "schedules": [
      {
        "date": "2026-04-02",
        "date_type": "schedule",
        "description": "」を出前館サイトで半額にて販売いたします。 (2)実施期間 2026年4月2日(木)～2026年4月8日(水) (3)対象店舗 出前館SD"
      },
      {
        "date": "2026-04-08",
        "date_type": "schedule",
        "description": "販売いたします。 (2)実施期間 2026年4月2日(木)～2026年4月8日(水) (3)対象店舗 出前館SD実施店舗 (4)対象商品"
      },
      {
        "date": "2026-04-14",
        "date_type": "schedule",
        "description": "UberEats社に負担していただきます。 (2)実施期間 2026年4月14日(火)～2026年4月27日(月) (3)対象店舗 Uber"
      },
      {
        "date": "2026-04-27",
        "date_type": "schedule",
        "description": "いただきます。 (2)実施期間 2026年4月14日(火)～2026年4月27日(月) (3)対象店舗 UberEats実施店舗　※Uber"
      },
      {
        "date": "2026-05-03",
        "date_type": "info",
        "description": "布期間(クーポン使用可能期間) 2026年4月27日(月)～2026年5月3日(日) (3)対象ユーザー Pontaパス会員(有料会員)"
      },
      {
        "date": "2026-03-19",
        "date_type": "info",
        "description": "キャンペーン 販促 半額 UB 外部配達 menu 公開日 2026/03/19 18:00 〜 タイトル 【GT】4月度宅配CPの参加につ"
      },
      {
        "date": "2026-05-31",
        "date_type": "deadline",
        "description": "クルー 業務通達 発行部門 営業サポートグループ 掲示期限 2026/05/31 発行責任者 ディレクター　林田　洋一 ※必要時のみ印刷して"
      },
      {
        "date": "0422-37-55",
        "date_type": "info",
        "description": "オペレーションチーム　　IP:9#100-5523  外線:0422-37-5501 （平日9時～18時） 【通達添付】4月GTキャンペーン"
      },
      {
        "date": "2026-04-03",
        "date_type": "deadline",
        "description": "する 印刷する 作業を登録する 店舗メモを登録する ​ 〜 4月3日(金) キーワード 出前館 宅配 キャンペーン 販促 半額"
      }
    ],
    "fetched_at": "2026-03-31T15:52:15.719466"
  },
  {
    "id": "200454",
    "category": "連絡",
    "title": "【26年4月度】すかいらーく 感じよい勉強会開催について",
    "date": "2026/03/17 10:00",
    "department": "営業政策チーム",
    "body": "",
    "pdfs": [],
    "schedules": [],
    "fetched_at": "2026-03-31T15:52:15.719466"
  },
  {
    "id": "199473",
    "category": "2026年 春期消防訓練の実施について",
    "title": "防災チェック実施報告 (通達の回答フォームより報告)",
    "date": "2026/03/09〜06/10",
    "department": "岩永　飛鳥",
    "body": "",
    "pdfs": [],
    "schedules": [],
    "fetched_at": "2026-03-31T16:32:32.006753"
  },
  {
    "id": "199430",
    "category": "4月雇用契約更新時の注意点について",
    "title": "クルー雇用契約更新",
    "date": "2026/03/06〜31",
    "department": "岩永　飛鳥",
    "body": "",
    "pdfs": [],
    "schedules": [],
    "fetched_at": "2026-03-31T15:52:15.719466"
  },
  {
    "id": "199828",
    "category": "【クルー対象】クルーアンケートの実施について",
    "title": "クルーアンケート通達掲示",
    "date": "2026/03/02〜31",
    "department": "岩永　飛鳥",
    "body": "",
    "pdfs": [],
    "schedules": [],
    "fetched_at": "2026-03-31T15:52:15.719466"
  },
  {
    "id": "199403",
    "category": "連絡",
    "title": "2026年春期健康診断について（GT・JS）",
    "date": "2026/02/10 18:00",
    "department": "健康・労務チーム",
    "body": "",
    "pdfs": [],
    "schedules": [],
    "fetched_at": "2026-03-31T15:52:15.719466"
  },
  {
    "id": "200964",
    "category": "連絡",
    "title": "すかいらーくグループ取締役の異動について",
    "date": "16:00",
    "department": "法務コンプライアンスチーム",
    "body": "",
    "pdfs": [],
    "schedules": [],
    "fetched_at": "2026-03-31T16:32:32.006753"
  },
  {
    "id": "200948",
    "category": "連絡",
    "title": "2026年4月1日付　組織改定および人事異動について",
    "date": "16:00",
    "department": "人事担当チーム",
    "body": "",
    "pdfs": [],
    "schedules": [
      {
        "date": "2026-04-01",
        "date_type": "info",
        "description": "2026年4月1日付　組織改定および人事異動について"
      }
    ],
    "fetched_at": "2026-03-31T16:32:32.006753"
  }
]